osutool/__init__.py
osutool/__main__.py
osutool-0.1.3.dist-info/LICENSE
osutool-0.1.3.dist-info/METADATA
osutool-0.1.3.dist-info/WHEEL
osutool-0.1.3.dist-info/entry_points.txt
osutool-0.1.3.dist-info/top_level.txt
osutool-0.1.3.dist-info/zip-safe
osutool-0.1.3.dist-info/RECORD
